<?xml version="1.0" encoding="utf-8" ?><dwsync><file name="arrow.gif" server="ftp.moradadigital.com//sitebuilder/" local="128828412000000000" remote="128828412000000000" Dst="-1" /><file name="bar.gif" server="ftp.moradadigital.com//sitebuilder/" local="128828412000000000" remote="128828412000000000" Dst="-1" /><file name="failed.png" server="ftp.moradadigital.com//sitebuilder/" local="128828412000000000" remote="128828412000000000" Dst="-1" /><file name="file.png" server="ftp.moradadigital.com//sitebuilder/" local="128828412000000000" remote="128828412000000000" Dst="-1" /><file name="folder.gif" server="ftp.moradadigital.com//sitebuilder/" local="128828412000000000" remote="128828412000000000" Dst="-1" /><file name="icon.gif" server="ftp.moradadigital.com//sitebuilder/" local="128828412000000000" remote="128828412000000000" Dst="-1" /><file name="progress.gif" server="ftp.moradadigital.com//sitebuilder/" local="128828412000000000" remote="128828412000000000" Dst="-1" /><file name="success.png" server="ftp.moradadigital.com//sitebuilder/" local="128828412000000000" remote="128828412000000000" Dst="-1" /><file name="uploading.png" server="ftp.moradadigital.com//sitebuilder/" local="128828412000000000" remote="128828412000000000" Dst="-1" /><file name="upload_back.gif" server="ftp.moradadigital.com//sitebuilder/" local="128828412000000000" remote="128828412000000000" Dst="-1" /><file name="arrow.gif" server="ftp.boxvenue.net//www/sitebuilder/" local="3485431788" remote="318763443877797132" Dst="-1" /><file name="bar.gif" server="ftp.boxvenue.net//www/sitebuilder/" local="3485431792" remote="318763443877797132" Dst="-1" /><file name="failed.png" server="ftp.boxvenue.net//www/sitebuilder/" local="3485431793" remote="318763443877797132" Dst="-1" /><file name="file.png" server="ftp.boxvenue.net//www/sitebuilder/" local="3485431794" remote="318763443877797132" Dst="-1" /><file name="folder.gif" server="ftp.boxvenue.net//www/sitebuilder/" local="3485431794" remote="318763443877797132" Dst="-1" /><file name="icon.gif" server="ftp.boxvenue.net//www/sitebuilder/" local="3485431795" remote="318763443877797132" Dst="-1" /><file name="progress.gif" server="ftp.boxvenue.net//www/sitebuilder/" local="3485431795" remote="318763443877797132" Dst="-1" /><file name="success.png" server="ftp.boxvenue.net//www/sitebuilder/" local="3485431795" remote="318763443877797132" Dst="-1" /><file name="upload_back.gif" server="ftp.boxvenue.net//www/sitebuilder/" local="3485431796" remote="318763443877797132" Dst="-1" /><file name="uploading.png" server="ftp.boxvenue.net//www/sitebuilder/" local="3485431796" remote="318763443877797132" Dst="-1" /></dwsync>