<?xml version="1.0" encoding="utf-8" ?>
<dwsync>
<file name="createdir.js" server="ftp.moradadigital.com//sitebuilder/" local="128335068000000000" remote="128335068000000000" />
<file name="createdoc.js" server="ftp.moradadigital.com//sitebuilder/" local="128335068000000000" remote="128335068000000000" />
<file name="dirlist.js" server="ftp.moradadigital.com//sitebuilder/" local="128552796000000000" remote="128552796000000000" />
<file name="filelist.js" server="ftp.moradadigital.com//sitebuilder/" local="128342844000000000" remote="128342844000000000" />
<file name="fileprops.js" server="ftp.moradadigital.com//sitebuilder/" local="128341116000000000" remote="128341116000000000" />
<file name="framesettoolshorizontal.js" server="ftp.moradadigital.com//sitebuilder/" local="128335068000000000" remote="128335068000000000" />
<file name="framesettoolsvertical.js" server="ftp.moradadigital.com//sitebuilder/" local="128335068000000000" remote="128335068000000000" />
<file name="general.js" server="ftp.moradadigital.com//sitebuilder/" local="128335068000000000" remote="128335068000000000" />
<file name="generallist.js" server="ftp.moradadigital.com//sitebuilder/" local="128388636000000000" remote="128388636000000000" />
<file name="paginglist.js" server="ftp.moradadigital.com//sitebuilder/" local="128335068000000000" remote="128335068000000000" />
<file name="preloadimages.js" server="ftp.moradadigital.com//sitebuilder/" local="128335068000000000" remote="128335068000000000" />
<file name="preview.js" server="ftp.moradadigital.com//sitebuilder/" local="128336796000000000" remote="128336796000000000" />
<file name="previewimage.js" server="ftp.moradadigital.com//sitebuilder/" local="128374812000000000" remote="128374812000000000" />
<file name="search.js" server="ftp.moradadigital.com//sitebuilder/" local="128335068000000000" remote="128335068000000000" />
<file name="thumbnails.js" server="ftp.moradadigital.com//sitebuilder/" local="128347164000000000" remote="128347164000000000" />
<file name="toolbar.js" server="ftp.moradadigital.com//sitebuilder/" local="128335068000000000" remote="128335068000000000" />
<file name="unzip.js" server="ftp.moradadigital.com//sitebuilder/" local="128339388000000000" remote="128339388000000000" />
<file name="upload.js" server="ftp.moradadigital.com//sitebuilder/" local="128375676000000000" remote="128375676000000000" />
<file name="zip.js" server="ftp.moradadigital.com//sitebuilder/" local="128335068000000000" remote="128335068000000000" />
</dwsync>