<?xml version="1.0" encoding="utf-8" ?><dwsync><file name="add_content.gif" server="ftp.moradadigital.com//sitebuilder/" local="128780028000000000" remote="128780028000000000" Dst="-1" /><file name="eng_project.gif" server="ftp.moradadigital.com//sitebuilder/" local="128780028000000000" remote="128780028000000000" Dst="-1" /><file name="header.gif" server="ftp.moradadigital.com//sitebuilder/" local="128967945000000000" remote="128967945000000000" Dst="-1" /><file name="header.jpg" server="ftp.moradadigital.com//sitebuilder/" local="128780028000000000" remote="128780028000000000" Dst="-1" /><file name="lock.gif" server="ftp.moradadigital.com//sitebuilder/" local="128837052000000000" remote="128837052000000000" Dst="-1" /><file name="log.gif" server="ftp.moradadigital.com//sitebuilder/" local="128987945948365637" remote="128987946600000000" Dst="-1" /><file name="login.gif" server="ftp.moradadigital.com//sitebuilder/" local="128987946561300695" remote="128987946600000000" Dst="-1" /><file name="my_content.png" server="ftp.moradadigital.com//sitebuilder/" local="128780028000000000" remote="128780028000000000" Dst="-1" /><file name="my_contents.gif" server="ftp.moradadigital.com//sitebuilder/" local="128780028000000000" remote="128780028000000000" Dst="-1" /><file name="no_avatar.gif" server="ftp.moradadigital.com//sitebuilder/" local="128780028000000000" remote="128780028000000000" Dst="-1" /><file name="ok.jpg" server="ftp.moradadigital.com//sitebuilder/" local="128780028000000000" remote="128780028000000000" Dst="-1" /><file name="panel.gif" server="ftp.moradadigital.com//sitebuilder/" local="128780028000000000" remote="128780028000000000" Dst="-1" /><file name="password.jpg" server="ftp.moradadigital.com//sitebuilder/" local="128780028000000000" remote="128780028000000000" Dst="-1" /><file name="registe_se.jpg" server="ftp.moradadigital.com//sitebuilder/" local="128780028000000000" remote="128780028000000000" Dst="-1" /><file name="registe_se.png" server="ftp.moradadigital.com//sitebuilder/" local="128780028000000000" remote="128780028000000000" Dst="-1" /><file name="scheduled-backup.jpg" server="ftp.moradadigital.com//sitebuilder/" local="128780028000000000" remote="128780028000000000" Dst="-1" /><file name="security_img1.jpg" server="ftp.moradadigital.com//sitebuilder/" local="128780028000000000" remote="128780028000000000" Dst="-1" /><file name="security_img2.jpg" server="ftp.moradadigital.com//sitebuilder/" local="128780028000000000" remote="128780028000000000" Dst="-1" /><file name="security_img3.jpg" server="ftp.moradadigital.com//sitebuilder/" local="128780028000000000" remote="128780028000000000" Dst="-1" /><file name="security_img4.jpg" server="ftp.moradadigital.com//sitebuilder/" local="128780028000000000" remote="128780028000000000" Dst="-1" /><file name="seta.gif" server="ftp.moradadigital.com//sitebuilder/" local="128780028000000000" remote="128780028000000000" Dst="-1" /><file name="space.gif" server="ftp.moradadigital.com//sitebuilder/" local="128780028000000000" remote="128780028000000000" Dst="-1" /><file name="Thumbs.db" server="ftp.moradadigital.com//sitebuilder/" local="128780028000000000" remote="128780028000000000" Dst="-1" /><file name="tweak.gif" server="ftp.moradadigital.com//sitebuilder/" local="128780028000000000" remote="128780028000000000" Dst="-1" /><file name="upload.gif" server="ftp.moradadigital.com//sitebuilder/" local="128780028000000000" remote="128780028000000000" Dst="-1" /><file name="user-profile.gif" server="ftp.moradadigital.com//sitebuilder/" local="128780028000000000" remote="128780028000000000" Dst="-1" /><file name="user-profile.jpg" server="ftp.moradadigital.com//sitebuilder/" local="128780028000000000" remote="128780028000000000" Dst="-1" /><file name="warning.gif" server="ftp.moradadigital.com//sitebuilder/" local="128780028000000000" remote="128780028000000000" Dst="-1" /><file name="question-mark.jpg" server="ftp.moradadigital.com//sitebuilder/" local="128969677800000000" remote="128969677800000000" Dst="-1" /><file name="email.jpg" server="ftp.moradadigital.com//sitebuilder/" local="128969676600000000" remote="128969676600000000" Dst="-1" /><file name="email.gif" server="ftp.moradadigital.com//sitebuilder/" local="128969677800000000" remote="128969677800000000" Dst="-1" /><file name="check_mark.gif" server="ftp.moradadigital.com//sitebuilder/" local="127657692000000000" remote="128989708800000000" Dst="-1" /><file name="cross_mark.gif" server="ftp.moradadigital.com//sitebuilder/" local="127657692000000000" remote="128989708800000000" Dst="-1" /><file name="add_content.gif" server="ftp.boxvenue.net//www/sitebuilder/" local="3316374000" remote="318763443877809432" Dst="-1" /><file name="check_mark.gif" server="ftp.boxvenue.net//www/sitebuilder/" local="3204140400" remote="318763443877809432" Dst="-1" /><file name="cross_mark.gif" server="ftp.boxvenue.net//www/sitebuilder/" local="3204140400" remote="318763443877809432" Dst="-1" /><file name="email.gif" server="ftp.boxvenue.net//www/sitebuilder/" local="3335338980" remote="318763443877809432" Dst="-1" /><file name="email.jpg" server="ftp.boxvenue.net//www/sitebuilder/" local="3335338860" remote="318763443877809432" Dst="-1" /><file name="eng_project.gif" server="ftp.boxvenue.net//www/sitebuilder/" local="3316374000" remote="318763443877809432" Dst="-1" /><file name="header.gif" server="ftp.boxvenue.net//www/sitebuilder/" local="3335165700" remote="318763443877809432" Dst="-1" /><file name="header.jpg" server="ftp.boxvenue.net//www/sitebuilder/" local="3316374000" remote="318763443877809432" Dst="-1" /><file name="lock.gif" server="ftp.boxvenue.net//www/sitebuilder/" local="3322076400" remote="318763443877809432" Dst="-1" /><file name="log.gif" server="ftp.boxvenue.net//www/sitebuilder/" local="3337165796" remote="318763443877809432" Dst="-1" /><file name="login.gif" server="ftp.boxvenue.net//www/sitebuilder/" local="3337165858" remote="318763443877809432" Dst="-1" /><file name="my_content.png" server="ftp.boxvenue.net//www/sitebuilder/" local="3316374000" remote="318763443877809432" Dst="-1" /><file name="my_contents.gif" server="ftp.boxvenue.net//www/sitebuilder/" local="3316374000" remote="318763443877809432" Dst="-1" /><file name="no_avatar.gif" server="ftp.boxvenue.net//www/sitebuilder/" local="3316374000" remote="318763443877809432" Dst="-1" /><file name="ok.jpg" server="ftp.boxvenue.net//www/sitebuilder/" local="3316374000" remote="318763443877809432" Dst="-1" /><file name="panel.gif" server="ftp.boxvenue.net//www/sitebuilder/" local="3316374000" remote="318763443877809432" Dst="-1" /><file name="password.jpg" server="ftp.boxvenue.net//www/sitebuilder/" local="3316374000" remote="318763443877809432" Dst="-1" /><file name="question-mark.jpg" server="ftp.boxvenue.net//www/sitebuilder/" local="3335338980" remote="318763443877809432" Dst="-1" /><file name="registe_se.jpg" server="ftp.boxvenue.net//www/sitebuilder/" local="3316374000" remote="318763443877809432" Dst="-1" /><file name="registe_se.png" server="ftp.boxvenue.net//www/sitebuilder/" local="3316374000" remote="318763443877809432" Dst="-1" /><file name="scheduled-backup.jpg" server="ftp.boxvenue.net//www/sitebuilder/" local="3316374000" remote="318763443877809432" Dst="-1" /><file name="security_img1.jpg" server="ftp.boxvenue.net//www/sitebuilder/" local="3316374000" remote="318763443877809432" Dst="-1" /><file name="security_img2.jpg" server="ftp.boxvenue.net//www/sitebuilder/" local="3316374000" remote="318763443877809432" Dst="-1" /><file name="security_img3.jpg" server="ftp.boxvenue.net//www/sitebuilder/" local="3316374000" remote="318763443877809432" Dst="-1" /><file name="security_img4.jpg" server="ftp.boxvenue.net//www/sitebuilder/" local="3316374000" remote="318763443877809432" Dst="-1" /><file name="seta.gif" server="ftp.boxvenue.net//www/sitebuilder/" local="3316374000" remote="318763443877809432" Dst="-1" /><file name="space.gif" server="ftp.boxvenue.net//www/sitebuilder/" local="3316374000" remote="318763443877809432" Dst="-1" /><file name="Thumbs.db" server="ftp.boxvenue.net//www/sitebuilder/" local="3316374000" remote="318763443877809432" Dst="-1" /><file name="tweak.gif" server="ftp.boxvenue.net//www/sitebuilder/" local="3316374000" remote="318763443877809432" Dst="-1" /><file name="upload.gif" server="ftp.boxvenue.net//www/sitebuilder/" local="3316374000" remote="318763443877809432" Dst="-1" /><file name="user-profile.gif" server="ftp.boxvenue.net//www/sitebuilder/" local="3316374000" remote="318763443877809432" Dst="-1" /><file name="user-profile.jpg" server="ftp.boxvenue.net//www/sitebuilder/" local="3316374000" remote="318763443877809432" Dst="-1" /><file name="warning.gif" server="ftp.boxvenue.net//www/sitebuilder/" local="3316374000" remote="318763443877809432" Dst="-1" /></dwsync>